<?xml version="1.0" encoding="UTF-8"?>

<!DOCTYPE mapper
	PUBLIC "-//mybatis.org//DTD Mapper 3.0//EN"
	"http://mybatis.org/dtd/mybatis-3-mapper.dtd">

<mapper namespace="mapper.paticipant">
	<resultMap id="paticipantResult" type="paticipantVO">
		<result property="paticipant_seq" column="paticipant_seq" />
		<result property="receipts_seq" column="receipts_seq" />
		<result property="status" column="status" />
		<result property="line_seq" column="line_seq" />
		<result property="name" column="name" />
		<result property="id" column="id" />
		<result property="pos" column="pos" />
		<result property="regdate" column="regdate" />
		<result property="upddate" column="upddate" />
	</resultMap>
	
<insert id="ParticipantWrite" parameterType="paticipantVO">
    insert into paticipant
    values(#{paticipant_seq}, #{receipts_seq}, #{status}, #{line_seq}, #{name},
    #{id}, #{pos}, #{regdate}, #{upddate})
</insert>
 
</mapper>